mtune/__init__.py
mtune/mtune.py
mtune-1.1.1.dist-info/METADATA
mtune-1.1.1.dist-info/WHEEL
mtune-1.1.1.dist-info/top_level.txt
mtune-1.1.1.dist-info/RECORD
