Metadata-Version: 2.1
Name: mtune
Version: 1.1.1
Summary: Python package
Author: Dr. Selvaraman Nagamani, Gori Sankar Borah, Hillul Chutia 
Author-email: nagamaniselvaraman@gmail.com, gorishankarbora45@gmail.com, hillulchutia@gmail.com
Classifier: Programming Language :: Python :: 3
Requires-Python: >=3.11
Requires-Dist: numpy
Requires-Dist: pandas
Requires-Dist: scikit-learn
